odoo8_addon_pos_default_empty_image-8.0.0.1.1-py2.7-nspkg.pth
odoo8_addon_pos_default_empty_image-8.0.0.1.1.dist-info/DESCRIPTION.rst
odoo8_addon_pos_default_empty_image-8.0.0.1.1.dist-info/METADATA
odoo8_addon_pos_default_empty_image-8.0.0.1.1.dist-info/RECORD
odoo8_addon_pos_default_empty_image-8.0.0.1.1.dist-info/WHEEL
odoo8_addon_pos_default_empty_image-8.0.0.1.1.dist-info/metadata.json
odoo8_addon_pos_default_empty_image-8.0.0.1.1.dist-info/namespace_packages.txt
odoo8_addon_pos_default_empty_image-8.0.0.1.1.dist-info/top_level.txt
odoo_addons/pos_default_empty_image/README.rst
odoo_addons/pos_default_empty_image/__init__.py
odoo_addons/pos_default_empty_image/__openerp__.py
odoo_addons/pos_default_empty_image/models/__init__.py
odoo_addons/pos_default_empty_image/models/product_product.py
odoo_addons/pos_default_empty_image/static/src/js/pos_default_empty_image.js
odoo_addons/pos_default_empty_image/view/view.xml
