Metadata-Version: 2.0
Name: odoo8-addon-pos-default-empty-image
Version: 8.0.0.1.1
Summary: Optimise load time for products with no image
Home-page: https://akretion.com
Author: Akretion, GRAP, Odoo Community Association (OCA)
Author-email: support@odoo-community.org
License: AGPL-3
Platform: UNKNOWN
Classifier: Programming Language :: Python :: 2.7
Classifier: Framework :: Odoo
Classifier: License :: OSI Approved :: GNU Affero General Public License v3
Requires-Dist: odoo (<9.0a,>=8.0a)
